<?xml version="1.0"?>
<pfsensepkgs>
    <package>
        <name>API</name>
        <internal_name>api</internal_name>
        <descr><![CDATA[The missing REST API package for pfSense]]></descr>
        <website>https://github.com/jaredhendrickson13/pfsense-api</website>
        <category>System</category>
        <version>%%PKGVERSION%%</version>
        <configurationfile>api.xml</configurationfile>
        <maintainer>github@jaredhendrickson.com</maintainer>
        <conf>
				<enable></enable>
                <persist></persist>
				<allowed_interfaces>any</allowed_interfaces>
                <authmode>local</authmode>
				<content_type>json</content_type>
                <server_key></server_key>
                <jwt_exp>3600</jwt_exp>
				<keyhash>sha256</keyhash>
				<keybytes>16</keybytes>
				<keys></keys>
                <enable_login_protection></enable_login_protection>
        </conf>
    </package>
</pfsensepkgs>